{
  "post_id": "1lm98z7",
  "fetched_at": "2025-06-29T11:05:54.427477365+10:00",
  "comments": [
    {
      "id": "n05tauf",
      "body": "This is fantastic. Even if some scenarios regress, having someone out there tinkering with possible ways to further speed up decoding gets me excited; I honestly thought we'd hit the limit of what kind of speed we'd see on the Mac side by way of prompt processing, so just knowing you're out there doing this makes me really happy.\n\nYou mention specifically the requirements being the 0.6b; is that just to repeat your results and it could theoretically work on the larger models, or is it very specific to the 0.6b atm?",
      "parent_id": "t3_1lm98z7",
      "author": "SomeOddCodeGuy",
      "score": 21,
      "created": "2025-06-28T00:21:25Z"
    },
    {
      "id": "n064lv3",
      "body": "Love this. Been using the OpenEvolve playing around. Love this example as it might be able to adapt to some methodology I'm interested in. Thank you for working on this.",
      "parent_id": "t3_1lm98z7",
      "author": "minnsoup",
      "score": 6,
      "created": "2025-06-28T01:31:29Z"
    },
    {
      "id": "n064sfu",
      "body": "This is awesome, I enjoyed learning about it!",
      "parent_id": "t3_1lm98z7",
      "author": "Worth_Contract7903",
      "score": 2,
      "created": "2025-06-28T01:32:39Z"
    },
    {
      "id": "n066oy1",
      "body": "Thank you for the write-up! This is very inspiring",
      "parent_id": "t3_1lm98z7",
      "author": "DumaDuma",
      "score": 2,
      "created": "2025-06-28T01:44:47Z"
    },
    {
      "id": "n07sfu0",
      "body": "Do you have plans to add a UI for OpenEvolve? Could you?",
      "parent_id": "t3_1lm98z7",
      "author": "jazir5",
      "score": 2,
      "created": "2025-06-28T09:43:56Z"
    },
    {
      "id": "n08gvm9",
      "body": "Any interest in using openevolve et al. for [sparse attention mechanisms](https://www.tilderesearch.com/blog/sparse-attn)? 📊 \n\nFigure we’ll eventually see those gains everywhere; just trying to self-pace also 🏃",
      "parent_id": "t3_1lm98z7",
      "author": "Accomplished_Mode170",
      "score": 2,
      "created": "2025-06-28T13:01:44Z"
    }
  ],
  "raw_api_url": "/comments/1lm98z7"
}